csv2json.py
nx_csv2json-0.3.0.dist-info/METADATA
nx_csv2json-0.3.0.dist-info/WHEEL
nx_csv2json-0.3.0.dist-info/entry_points.txt
nx_csv2json-0.3.0.dist-info/top_level.txt
nx_csv2json-0.3.0.dist-info/RECORD
